necoplot/__init__.py
necoplot/common.py
necoplot/config.py
necoplot/extract_params.py
necoplot/multi_plot.py
necoplot/plot_base.py
necoplot/single_plot.py
necoplot/slope_plot.py
necoplot-0.1.5.dist-info/LICENSE
necoplot-0.1.5.dist-info/WHEEL
necoplot-0.1.5.dist-info/METADATA
necoplot-0.1.5.dist-info/RECORD
