Metadata-Version: 2.1
Name: necoplot
Version: 0.1.5
Summary: A matplotlib wrapper; It may help you to write plotting code briefly.
Home-page: https://github.com/guneco
License: MIT
Author: guneco
Author-email: gu3fav@gmail.com
Requires-Python: >=3.8,<3.11
Classifier: License :: OSI Approved :: MIT License
Classifier: Programming Language :: Python :: 3
Classifier: Programming Language :: Python :: 3.10
Classifier: Programming Language :: Python :: 3.8
Classifier: Programming Language :: Python :: 3.9
Requires-Dist: japanize-matplotlib (>=1.1.3,<2.0.0)
Requires-Dist: matplotlib (>=3.5.1,<4.0.0)
